popdelta/.DS_Store
popdelta/__init__.py
popdelta/format_ouput.py
popdelta/hot_encoder.py
popdelta/miner.py
popdelta/pop_delta.py
popdelta/pop_delta1.py
popdelta/pop_delta2.py
popdelta/settings.py
popdelta-0.0.2.dist-info/METADATA
popdelta-0.0.2.dist-info/WHEEL
popdelta-0.0.2.dist-info/licenses/LICENSE
popdelta-0.0.2.dist-info/RECORD
