Metadata-Version: 2.1
Name: popdelta
Version: 0.0.2
Summary: PopDelta is a Python package for calculating the delta between two populations.
Project-URL: Homepage, https://github.com/einblick-ai/PopDelta
Project-URL: Bug Tracker, https://github.com/einblick-ai/PopDelta/issues
Author-email: "B.J. Buratti" <bb@einblick.ai>
License-File: LICENSE
Classifier: License :: OSI Approved :: MIT License
Classifier: Operating System :: OS Independent
Classifier: Programming Language :: Python :: 3
Requires-Python: >=3.7
Requires-Dist: numpy>=1.19.2
Requires-Dist: pandas>=1.5.2
Requires-Dist: pyfim>=6.28
